marshmallow_annotations/__init__.py
marshmallow_annotations/_compat.py
marshmallow_annotations/base.py
marshmallow_annotations/converter.py
marshmallow_annotations/exceptions.py
marshmallow_annotations/registry.py
marshmallow_annotations/scheme.py
marshmallow_annotations/ext/__init__.py
marshmallow_annotations/ext/attrs.py
marshmallow_annotations/ext/namedtuple.py
marshmallow_annotations-2.4.0.dist-info/AUTHORS.rst
marshmallow_annotations-2.4.0.dist-info/LICENSE
marshmallow_annotations-2.4.0.dist-info/METADATA
marshmallow_annotations-2.4.0.dist-info/WHEEL
marshmallow_annotations-2.4.0.dist-info/top_level.txt
marshmallow_annotations-2.4.0.dist-info/RECORD
