Metadata-Version: 2.1
Name: marshmallow-annotations
Version: 2.4.0
Summary: Marrying marshmallow and annotations
Home-page: https://github.com/justanr/marshmallow-annotations
Author: Alec Nikolas Reiter
Author-email: alecreiter@gmail.com
License: MIT
Keywords: annotations,marshmallow
Platform: UNKNOWN
Classifier: Topic :: Utilities
Classifier: Intended Audience :: Developers
Classifier: License :: OSI Approved :: MIT License
Classifier: Programming Language :: Python :: 3.6
Classifier: Programming Language :: Python :: Implementation :: CPython
Requires-Dist: marshmallow (<3.0.0,>=2.0.0)
Provides-Extra: attrs
Requires-Dist: attrs ; extra == 'attrs'
